{"version": 0.6, "generator": "Overpass API 0.7.62.8 e802775f", "osm3s": {"timestamp_osm_base": "2026-01-13T20:19:44Z", "copyright": "The data included in this document is from www.openstreetmap.org. The data is made available under ODbL."}, "elements": [{"type": "node", "id": 1511959432, "lat": 48.8379701, "lon": 2.3356392, "tags": {"addr:city": "Paris", "addr:housenumber": "68 Bis", "addr:street": "Avenue Denfert-Rochereau", "email": "contact@artisanatmonastique.com", "fair_trade": "yes", "fax": "+33 1 43 35 14 43", "name": "L'Artisanat Monastique", "opening_hours": "Tu-Sa 12:00-19:00", "phone": "+33 1 43 35 15 76", "shop": "deli;gift", "source": "cadastre-dgi-fr source : Direction G\u00e9n\u00e9rale des Imp\u00f4ts - Cadastre;mise \u00e0 jour : 2011", "website": "https://www.artisanatmonastique.com/"}}, {"type": "node", "id": 1664328016, "lat": 48.8389698, "lon": 2.33252, "tags": {"name": "Atelier Gustave", "shop": "art"}}, {"type": "node", "id": 7300283178, "lat": 48.8386049, "lon": 2.3311462, "tags": {"level": "0", "shop": "convenience", "wheelchair": "limited"}}, {"type": "node", "id": 7424865385, "lat": 48.8379799, "lon": 2.3362769, "tags": {"check_date": "2022-10-29", "shop": "vacant"}}, {"type": "node", "id": 7448067386, "lat": 48.8377998, "lon": 2.3359766, "tags": {"check_date": "2023-05-25", "check_date:opening_hours": "2023-05-20", "name": "Royal Lotus", "opening_hours:signed": "no", "shop": "massage", "wheelchair": "no"}}, {"type": "node", "id": 8763382353, "lat": 48.8378992, "lon": 2.3315821, "tags": {"name": "V\u00e9loTime", "opening_hours": "Mo-Su 10:30-12:45,14:00-18:00", "shop": "bicycle", "wheelchair": "no"}}]}